ecstacy-0.1.0.dist-info/METADATA
ecstacy-0.1.0.dist-info/WHEEL
ecstacy/py.typed
ecstacy/ecstacy.pyi
ecstacy/__init__.py
ecstacy/_internal/__init__.py
ecstacy/ecstacy.cpython-311-x86_64-linux-gnu.so
ecstacy-0.1.0.dist-info/RECORD
