Metadata-Version: 2.1
Name: ecstacy
Version: 0.1.0
Classifier: Programming Language :: Rust
Classifier: Programming Language :: Python :: Implementation :: CPython
Classifier: Programming Language :: Python :: Implementation :: PyPy
Requires-Dist: numpy
Requires-Dist: black; extra == 'dev'
Requires-Dist: ruff; extra == 'dev'
Requires-Dist: mypy; extra == 'dev'
Requires-Dist: pytest; extra == 'dev'
Requires-Dist: pytest-benchmark; extra == 'dev'
Provides-Extra: dev
Requires-Python: >=3.11
